raf/__init__.py
raf/__main__.py
raf/binary_dependencies/ffmpeg
raf/binary_dependencies/ffmpeg.exe
raf/binary_dependencies/flac
raf/binary_dependencies/flac.exe
rebuild_audio_file-0.1.1.dist-info/LICENSE
rebuild_audio_file-0.1.1.dist-info/METADATA
rebuild_audio_file-0.1.1.dist-info/WHEEL
rebuild_audio_file-0.1.1.dist-info/entry_points.txt
rebuild_audio_file-0.1.1.dist-info/top_level.txt
rebuild_audio_file-0.1.1.dist-info/RECORD
